VPGen/Classes.py
VPGen/Generator.py
VPGen/IO.py
VPGen/Plot.py
VPGen/VPGen.dll
VPGen/VPGen.so
VPGen/__init__.py
VPGen/Old/__core.py
VPGen/Old/__init__.py
VPGen/Old/__pgen/__area.py
VPGen/Old/__pgen/__chess.py
VPGen/Old/__pgen/__init__.py
VPGen/Old/__pgen/__inline.py
VPGen/Old/__pgen/__random.py
VPGen/Old/__vgen/__area.py
VPGen/Old/__vgen/__chess.py
VPGen/Old/__vgen/__init__.py
VPGen/Old/__vgen/__inline.py
VPGen/Old/__vgen/__random.py
VPGen-1.0.0.dist-info/LICENSE
VPGen-1.0.0.dist-info/METADATA
VPGen-1.0.0.dist-info/WHEEL
VPGen-1.0.0.dist-info/top_level.txt
VPGen-1.0.0.dist-info/RECORD
