Metadata-Version: 2.1
Name: VPGen
Version: 1.0.0
Summary: Generate porosity medium
Author: Savvin Anton
Author-email: anv.savvin@gmail.com
License: GPL-3.0 license
Keywords: python
Platform: Windows
Platform: Unix
Classifier: Programming Language :: Python :: 3
License-File: LICENSE
